[{"Time":0.018000000000000002,"Method":"AntiAfkEventHandler","Class":"Common_Utilities.EventHandlers.PlayerHandlers"},{"Time":0.014700000000000001,"Method":"AntiAfkEventHandler","Class":"Common_Utilities.EventHandlers.PlayerHandlers"},{"Time":0.015600000000000001,"Method":"AntiAfkEventHandler","Class":"Common_Utilities.EventHandlers.PlayerHandlers"},{"Time":0.027100000000000003,"Method":"OnRoundEnding","Class":"SCPStats.EventHandler"},{"Time":0.0211,"Method":"AntiAfkEventHandler","Class":"Common_Utilities.EventHandlers.PlayerHandlers"},{"Time":0.0245,"Method":"OnInteractingDoor","Class":"DiscordIntegration.Events.PlayerHandler"},{"Time":0.016300000000000002,"Method":"OnDoorOpen","Class":"AdminTools.EventHandlers"},{"Time":0.011300000000000001,"Method":"OnPlayerInteractingDoor","Class":"AdminTools.EventHandlers"},{"Time":0.0204,"Method":"OnInteractingDoor","Class":"Common_Utilities.EventHandlers.PlayerHandlers"},{"Time":0.0442,"Method":"OnDoorInteract","Class":"RemoteKeycard.EventsHandler"},{"Time":0.029500000000000002,"Method":"OnInteractingDoor","Class":"FbiOpenUp.EventHandlers"},{"Time":0.0194,"Method":"AntiAfkEventHandler","Class":"Common_Utilities.EventHandlers.PlayerHandlers"},{"Time":0.0284,"Method":"OnInteractingDoor","Class":"DiscordIntegration.Events.PlayerHandler"},{"Time":0.0145,"Method":"OnDoorOpen","Class":"AdminTools.EventHandlers"},{"Time":0.0119,"Method":"OnPlayerInteractingDoor","Class":"AdminTools.EventHandlers"},{"Time":0.029900000000000003,"Method":"OnInteractingDoor","Class":"Common_Utilities.EventHandlers.PlayerHandlers"},{"Time":0.042,"Method":"OnDoorInteract","Class":"RemoteKeycard.EventsHandler"},{"Time":0.0291,"Method":"OnInteractingDoor","Class":"FbiOpenUp.EventHandlers"},{"Time":0.0194,"Method":"AntiAfkEventHandler","Class":"Common_Utilities.EventHandlers.PlayerHandlers"},{"Time":0.033,"Method":"AntiAfkEventHandler","Class":"Common_Utilities.EventHandlers.PlayerHandlers"},{"Time":0.0171,"Method":"AntiAfkEventHandler","Class":"Common_Utilities.EventHandlers.PlayerHandlers"},{"Time":0.019100000000000002,"Method":"AntiAfkEventHandler","Class":"Common_Utilities.EventHandlers.PlayerHandlers"},{"Time":0.0176,"Method":"AntiAfkEventHandler","Class":"Common_Utilities.EventHandlers.PlayerHandlers"},{"Time":0.0112,"Method":"AntiAfkEventHandler","Class":"Common_Utilities.EventHandlers.PlayerHandlers"},{"Time":0.0142,"Method":"OnRoundEnding","Class":"SCPStats.EventHandler"},{"Time":0.047,"Method":"OnInteractingDoor","Class":"DiscordIntegration.Events.PlayerHandler"},{"Time":0.010400000000000001,"Method":"OnDoorOpen","Class":"AdminTools.EventHandlers"},{"Time":0.0090000000000000011,"Method":"OnPlayerInteractingDoor","Class":"AdminTools.EventHandlers"},{"Time":0.0183,"Method":"OnInteractingDoor","Class":"Common_Utilities.EventHandlers.PlayerHandlers"},{"Time":0.0539,"Method":"OnDoorInteract","Class":"RemoteKeycard.EventsHandler"},{"Time":0.04,"Method":"OnInteractingDoor","Class":"FbiOpenUp.EventHandlers"},{"Time":0.0213,"Method":"AntiAfkEventHandler","Class":"Common_Utilities.EventHandlers.PlayerHandlers"},{"Time":0.0238,"Method":"OnInteractingDoor","Class":"DiscordIntegration.Events.PlayerHandler"},{"Time":0.013800000000000002,"Method":"OnDoorOpen","Class":"AdminTools.EventHandlers"},{"Time":0.0092,"Method":"OnPlayerInteractingDoor","Class":"AdminTools.EventHandlers"},{"Time":0.0126,"Method":"OnInteractingDoor","Class":"Common_Utilities.EventHandlers.PlayerHandlers"},{"Time":0.0333,"Method":"OnDoorInteract","Class":"RemoteKeycard.EventsHandler"},{"Time":0.0281,"Method":"OnInteractingDoor","Class":"FbiOpenUp.EventHandlers"},{"Time":0.0165,"Method":"AntiAfkEventHandler","Class":"Common_Utilities.EventHandlers.PlayerHandlers"},{"Time":0.0205,"Method":"AntiAfkEventHandler","Class":"Common_Utilities.EventHandlers.PlayerHandlers"},{"Time":0.0148,"Method":"AntiAfkEventHandler","Class":"Common_Utilities.EventHandlers.PlayerHandlers"},{"Time":0.016300000000000002,"Method":"AntiAfkEventHandler","Class":"Common_Utilities.EventHandlers.PlayerHandlers"},{"Time":0.015700000000000002,"Method":"AntiAfkEventHandler","Class":"Common_Utilities.EventHandlers.PlayerHandlers"},{"Time":0.06770000000000001,"Method":"OnPlayerVerify","Class":"Exiled.CreditTags.Events.CreditsHandler"},{"Time":0.2599,"Method":"OnVerified","Class":"DiscordIntegration.Events.PlayerHandler"},{"Time":0.3311,"Method":"OnPlayerVerified","Class":"AdminTools.EventHandlers"},{"Time":0.0402,"Method":"OnPlayerVerified","Class":"Common_Utilities.EventHandlers.PlayerHandlers"},{"Time":0.19590000000000002,"Method":"OnJoin","Class":"SCPStats.EventHandler"},{"Time":0.0159,"Method":"AntiAfkEventHandler","Class":"Common_Utilities.EventHandlers.PlayerHandlers"},{"Time":0.0245,"Method":"OnRoundEnding","Class":"SCPStats.EventHandler"},{"Time":0.017400000000000002,"Method":"AntiAfkEventHandler","Class":"Common_Utilities.EventHandlers.PlayerHandlers"},{"Time":0.0178,"Method":"AntiAfkEventHandler","Class":"Common_Utilities.EventHandlers.PlayerHandlers"},{"Time":0.0181,"Method":"AntiAfkEventHandler","Class":"Common_Utilities.EventHandlers.PlayerHandlers"},{"Time":0.0162,"Method":"AntiAfkEventHandler","Class":"Common_Utilities.EventHandlers.PlayerHandlers"},{"Time":0.0268,"Method":"OnInteractingDoor","Class":"DiscordIntegration.Events.PlayerHandler"},{"Time":0.0181,"Method":"OnDoorOpen","Class":"AdminTools.EventHandlers"},{"Time":0.014100000000000001,"Method":"OnPlayerInteractingDoor","Class":"AdminTools.EventHandlers"},{"Time":0.012100000000000001,"Method":"OnInteractingDoor","Class":"Common_Utilities.EventHandlers.PlayerHandlers"},{"Time":0.044700000000000004,"Method":"OnDoorInteract","Class":"RemoteKeycard.EventsHandler"},{"Time":0.028200000000000003,"Method":"OnInteractingDoor","Class":"FbiOpenUp.EventHandlers"},{"Time":0.018600000000000002,"Method":"AntiAfkEventHandler","Class":"Common_Utilities.EventHandlers.PlayerHandlers"},{"Time":0.0376,"Method":"OnInteractingDoor","Class":"DiscordIntegration.Events.PlayerHandler"},{"Time":0.0114,"Method":"OnDoorOpen","Class":"AdminTools.EventHandlers"},{"Time":0.0166,"Method":"OnPlayerInteractingDoor","Class":"AdminTools.EventHandlers"},{"Time":0.012700000000000001,"Method":"OnInteractingDoor","Class":"Common_Utilities.EventHandlers.PlayerHandlers"},{"Time":0.0414,"Method":"OnDoorInteract","Class":"RemoteKeycard.EventsHandler"},{"Time":0.0322,"Method":"OnInteractingDoor","Class":"FbiOpenUp.EventHandlers"},{"Time":0.020300000000000002,"Method":"AntiAfkEventHandler","Class":"Common_Utilities.EventHandlers.PlayerHandlers"},{"Time":0.0181,"Method":"AntiAfkEventHandler","Class":"Common_Utilities.EventHandlers.PlayerHandlers"},{"Time":0.0199,"Method":"AntiAfkEventHandler","Class":"Common_Utilities.EventHandlers.PlayerHandlers"},{"Time":0.018600000000000002,"Method":"OnRoundEnding","Class":"SCPStats.EventHandler"},{"Time":0.0131,"Method":"AntiAfkEventHandler","Class":"Common_Utilities.EventHandlers.PlayerHandlers"},{"Time":0.018600000000000002,"Method":"AntiAfkEventHandler","Class":"Common_Utilities.EventHandlers.PlayerHandlers"},{"Time":0.026500000000000003,"Method":"OnInteractingDoor","Class":"DiscordIntegration.Events.PlayerHandler"},{"Time":0.012400000000000001,"Method":"OnDoorOpen","Class":"AdminTools.EventHandlers"},{"Time":0.0083,"Method":"OnPlayerInteractingDoor","Class":"AdminTools.EventHandlers"},{"Time":0.0123,"Method":"OnInteractingDoor","Class":"Common_Utilities.EventHandlers.PlayerHandlers"},{"Time":0.0345,"Method":"OnDoorInteract","Class":"RemoteKeycard.EventsHandler"},{"Time":0.028200000000000003,"Method":"OnInteractingDoor","Class":"FbiOpenUp.EventHandlers"},{"Time":0.0194,"Method":"AntiAfkEventHandler","Class":"Common_Utilities.EventHandlers.PlayerHandlers"},{"Time":0.0195,"Method":"AntiAfkEventHandler","Class":"Common_Utilities.EventHandlers.PlayerHandlers"},{"Time":0.0224,"Method":"AntiAfkEventHandler","Class":"Common_Utilities.EventHandlers.PlayerHandlers"},{"Time":0.0162,"Method":"AntiAfkEventHandler","Class":"Common_Utilities.EventHandlers.PlayerHandlers"},{"Time":0.0176,"Method":"AntiAfkEventHandler","Class":"Common_Utilities.EventHandlers.PlayerHandlers"},{"Time":0.035,"Method":"OnInteractingDoor","Class":"DiscordIntegration.Events.PlayerHandler"},{"Time":0.0164,"Method":"OnDoorOpen","Class":"AdminTools.EventHandlers"},{"Time":0.0084000000000000012,"Method":"OnPlayerInteractingDoor","Class":"AdminTools.EventHandlers"},{"Time":0.0109,"Method":"OnInteractingDoor","Class":"Common_Utilities.EventHandlers.PlayerHandlers"},{"Time":0.0391,"Method":"OnDoorInteract","Class":"RemoteKeycard.EventsHandler"},{"Time":0.0284,"Method":"OnInteractingDoor","Class":"FbiOpenUp.EventHandlers"},{"Time":0.024800000000000003,"Method":"OnInteractingDoor","Class":"DiscordIntegration.Events.PlayerHandler"},{"Time":0.0142,"Method":"OnDoorOpen","Class":"AdminTools.EventHandlers"},{"Time":0.0106,"Method":"OnPlayerInteractingDoor","Class":"AdminTools.EventHandlers"},{"Time":0.0193,"Method":"OnInteractingDoor","Class":"Common_Utilities.EventHandlers.PlayerHandlers"},{"Time":0.062,"Method":"OnDoorInteract","Class":"RemoteKeycard.EventsHandler"},{"Time":0.028800000000000003,"Method":"OnInteractingDoor","Class":"FbiOpenUp.EventHandlers"},{"Time":0.0176,"Method":"AntiAfkEventHandler","Class":"Common_Utilities.EventHandlers.PlayerHandlers"},{"Time":0.0181,"Method":"AntiAfkEventHandler","Class":"Common_Utilities.EventHandlers.PlayerHandlers"},{"Time":0.0175,"Method":"OnRoundEnding","Class":"SCPStats.EventHandler"},{"Time":0.0164,"Method":"AntiAfkEventHandler","Class":"Common_Utilities.EventHandlers.PlayerHandlers"},{"Time":0.0151,"Method":"AntiAfkEventHandler","Class":"Common_Utilities.EventHandlers.PlayerHandlers"},{"Time":0.0187,"Method":"AntiAfkEventHandler","Class":"Common_Utilities.EventHandlers.PlayerHandlers"},{"Time":0.016800000000000002,"Method":"AntiAfkEventHandler","Class":"Common_Utilities.EventHandlers.PlayerHandlers"},{"Time":0.011600000000000001,"Method":"AntiAfkEventHandler","Class":"Common_Utilities.EventHandlers.PlayerHandlers"},{"Time":0.0172,"Method":"AntiAfkEventHandler","Class":"Common_Utilities.EventHandlers.PlayerHandlers"},{"Time":0.0183,"Method":"AntiAfkEventHandler","Class":"Common_Utilities.EventHandlers.PlayerHandlers"},{"Time":0.0275,"Method":"OnRoundEnding","Class":"SCPStats.EventHandler"},{"Time":0.0146,"Method":"AntiAfkEventHandler","Class":"Common_Utilities.EventHandlers.PlayerHandlers"},{"Time":0.0442,"Method":"OnInteractingDoor","Class":"DiscordIntegration.Events.PlayerHandler"},{"Time":0.0115,"Method":"OnDoorOpen","Class":"AdminTools.EventHandlers"},{"Time":0.0077,"Method":"OnPlayerInteractingDoor","Class":"AdminTools.EventHandlers"},{"Time":0.0119,"Method":"OnInteractingDoor","Class":"Common_Utilities.EventHandlers.PlayerHandlers"},{"Time":0.033800000000000004,"Method":"OnDoorInteract","Class":"RemoteKeycard.EventsHandler"},{"Time":0.023100000000000002,"Method":"OnInteractingDoor","Class":"FbiOpenUp.EventHandlers"},{"Time":0.0262,"Method":"OnInteractingDoor","Class":"DiscordIntegration.Events.PlayerHandler"},{"Time":0.0119,"Method":"OnDoorOpen","Class":"AdminTools.EventHandlers"},{"Time":0.0546,"Method":"OnPlayerInteractingDoor","Class":"AdminTools.EventHandlers"},{"Time":0.0155,"Method":"OnInteractingDoor","Class":"Common_Utilities.EventHandlers.PlayerHandlers"},{"Time":0.033100000000000004,"Method":"OnDoorInteract","Class":"RemoteKeycard.EventsHandler"},{"Time":0.0274,"Method":"OnInteractingDoor","Class":"FbiOpenUp.EventHandlers"},{"Time":0.015700000000000002,"Method":"AntiAfkEventHandler","Class":"Common_Utilities.EventHandlers.PlayerHandlers"},{"Time":0.0198,"Method":"AntiAfkEventHandler","Class":"Common_Utilities.EventHandlers.PlayerHandlers"},{"Time":0.0292,"Method":"OnInteractingDoor","Class":"DiscordIntegration.Events.PlayerHandler"},{"Time":0.0137,"Method":"OnDoorOpen","Class":"AdminTools.EventHandlers"},{"Time":0.0111,"Method":"OnPlayerInteractingDoor","Class":"AdminTools.EventHandlers"},{"Time":0.044000000000000004,"Method":"OnInteractingDoor","Class":"Common_Utilities.EventHandlers.PlayerHandlers"},{"Time":0.044500000000000005,"Method":"OnDoorInteract","Class":"RemoteKeycard.EventsHandler"},{"Time":0.0279,"Method":"OnInteractingDoor","Class":"FbiOpenUp.EventHandlers"},{"Time":0.0224,"Method":"AntiAfkEventHandler","Class":"Common_Utilities.EventHandlers.PlayerHandlers"},{"Time":0.0179,"Method":"AntiAfkEventHandler","Class":"Common_Utilities.EventHandlers.PlayerHandlers"},{"Time":0.016,"Method":"AntiAfkEventHandler","Class":"Common_Utilities.EventHandlers.PlayerHandlers"},{"Time":4.7562000000000006,"Method":"OnInteractingLocker","Class":"DiscordIntegration.Events.PlayerHandler"},{"Time":2.1086,"Method":"OnLockerInteract","Class":"RemoteKeycard.EventsHandler"},{"Time":0.019200000000000002,"Method":"AntiAfkEventHandler","Class":"Common_Utilities.EventHandlers.PlayerHandlers"},{"Time":0.0173,"Method":"OnRoundEnding","Class":"SCPStats.EventHandler"},{"Time":2.5754,"Method":"OnPickingUpItem","Class":"DiscordIntegration.Events.PlayerHandler"},{"Time":3.3749000000000002,"Method":"OnPickup","Class":"SCPStats.EventHandler"},{"Time":0.024800000000000003,"Method":"OnPickingUpItem","Class":"DiscordIntegration.Events.PlayerHandler"},{"Time":0.11420000000000001,"Method":"OnPickup","Class":"SCPStats.EventHandler"},{"Time":0.018500000000000003,"Method":"AntiAfkEventHandler","Class":"Common_Utilities.EventHandlers.PlayerHandlers"},{"Time":0.0553,"Method":"AntiAfkEventHandler","Class":"Common_Utilities.EventHandlers.PlayerHandlers"},{"Time":0.0172,"Method":"AntiAfkEventHandler","Class":"Common_Utilities.EventHandlers.PlayerHandlers"},{"Time":0.018000000000000002,"Method":"AntiAfkEventHandler","Class":"Common_Utilities.EventHandlers.PlayerHandlers"},{"Time":0.0176,"Method":"AntiAfkEventHandler","Class":"Common_Utilities.EventHandlers.PlayerHandlers"},{"Time":0.020900000000000002,"Method":"AntiAfkEventHandler","Class":"Common_Utilities.EventHandlers.PlayerHandlers"},{"Time":0.0171,"Method":"AntiAfkEventHandler","Class":"Common_Utilities.EventHandlers.PlayerHandlers"},{"Time":0.0181,"Method":"AntiAfkEventHandler","Class":"Common_Utilities.EventHandlers.PlayerHandlers"},{"Time":0.0189,"Method":"OnRoundEnding","Class":"SCPStats.EventHandler"},{"Time":0.0182,"Method":"AntiAfkEventHandler","Class":"Common_Utilities.EventHandlers.PlayerHandlers"},{"Time":0.0151,"Method":"AntiAfkEventHandler","Class":"Common_Utilities.EventHandlers.PlayerHandlers"},{"Time":0.0131,"Method":"AntiAfkEventHandler","Class":"Common_Utilities.EventHandlers.PlayerHandlers"},{"Time":0.0178,"Method":"AntiAfkEventHandler","Class":"Common_Utilities.EventHandlers.PlayerHandlers"},{"Time":3.1879,"Method":"OnChangingItem","Class":"DiscordIntegration.Events.PlayerHandler"},{"Time":0.016900000000000002,"Method":"AntiAfkEventHandler","Class":"Common_Utilities.EventHandlers.PlayerHandlers"},{"Time":0.014100000000000001,"Method":"AntiAfkEventHandler","Class":"Common_Utilities.EventHandlers.PlayerHandlers"},{"Time":0.0188,"Method":"AntiAfkEventHandler","Class":"Common_Utilities.EventHandlers.PlayerHandlers"},{"Time":0.04,"Method":"AntiAfkEventHandler","Class":"Common_Utilities.EventHandlers.PlayerHandlers"},{"Time":0.021400000000000002,"Method":"AntiAfkEventHandler","Class":"Common_Utilities.EventHandlers.PlayerHandlers"},{"Time":0.021400000000000002,"Method":"AntiAfkEventHandler","Class":"Common_Utilities.EventHandlers.PlayerHandlers"},{"Time":0.019,"Method":"AntiAfkEventHandler","Class":"Common_Utilities.EventHandlers.PlayerHandlers"},{"Time":0.0152,"Method":"OnRoundEnding","Class":"SCPStats.EventHandler"},{"Time":0.0236,"Method":"OnInteractingDoor","Class":"DiscordIntegration.Events.PlayerHandler"},{"Time":0.0105,"Method":"OnDoorOpen","Class":"AdminTools.EventHandlers"},{"Time":0.0075000000000000006,"Method":"OnPlayerInteractingDoor","Class":"AdminTools.EventHandlers"},{"Time":0.0112,"Method":"OnInteractingDoor","Class":"Common_Utilities.EventHandlers.PlayerHandlers"},{"Time":1.8738000000000001,"Method":"OnDoorInteract","Class":"RemoteKeycard.EventsHandler"},{"Time":0.0239,"Method":"OnInteractingDoor","Class":"FbiOpenUp.EventHandlers"},{"Time":0.027700000000000002,"Method":"OnInteractingDoor","Class":"DiscordIntegration.Events.PlayerHandler"},{"Time":0.0145,"Method":"OnDoorOpen","Class":"AdminTools.EventHandlers"},{"Time":0.0091,"Method":"OnPlayerInteractingDoor","Class":"AdminTools.EventHandlers"},{"Time":0.0143,"Method":"OnInteractingDoor","Class":"Common_Utilities.EventHandlers.PlayerHandlers"},{"Time":0.3052,"Method":"OnDoorInteract","Class":"RemoteKeycard.EventsHandler"},{"Time":0.0483,"Method":"OnInteractingDoor","Class":"FbiOpenUp.EventHandlers"},{"Time":0.015600000000000001,"Method":"AntiAfkEventHandler","Class":"Common_Utilities.EventHandlers.PlayerHandlers"},{"Time":0.0178,"Method":"AntiAfkEventHandler","Class":"Common_Utilities.EventHandlers.PlayerHandlers"},{"Time":0.1134,"Method":"AntiAfkEventHandler","Class":"Common_Utilities.EventHandlers.PlayerHandlers"},{"Time":0.0171,"Method":"AntiAfkEventHandler","Class":"Common_Utilities.EventHandlers.PlayerHandlers"},{"Time":0.0155,"Method":"AntiAfkEventHandler","Class":"Common_Utilities.EventHandlers.PlayerHandlers"},{"Time":0.0161,"Method":"AntiAfkEventHandler","Class":"Common_Utilities.EventHandlers.PlayerHandlers"},{"Time":0.0125,"Method":"AntiAfkEventHandler","Class":"Common_Utilities.EventHandlers.PlayerHandlers"},{"Time":0.0166,"Method":"OnRoundEnding","Class":"SCPStats.EventHandler"},{"Time":0.0152,"Method":"AntiAfkEventHandler","Class":"Common_Utilities.EventHandlers.PlayerHandlers"},{"Time":0.0154,"Method":"AntiAfkEventHandler","Class":"Common_Utilities.EventHandlers.PlayerHandlers"},{"Time":0.0238,"Method":"OnInteractingDoor","Class":"DiscordIntegration.Events.PlayerHandler"},{"Time":0.0103,"Method":"OnDoorOpen","Class":"AdminTools.EventHandlers"},{"Time":0.0077,"Method":"OnPlayerInteractingDoor","Class":"AdminTools.EventHandlers"},{"Time":0.0112,"Method":"OnInteractingDoor","Class":"Common_Utilities.EventHandlers.PlayerHandlers"},{"Time":0.0998,"Method":"OnDoorInteract","Class":"RemoteKeycard.EventsHandler"},{"Time":0.021500000000000002,"Method":"OnInteractingDoor","Class":"FbiOpenUp.EventHandlers"},{"Time":0.0142,"Method":"AntiAfkEventHandler","Class":"Common_Utilities.EventHandlers.PlayerHandlers"},{"Time":2.4845,"Method":"OnUsedMedicalItem","Class":"DiscordIntegration.Events.PlayerHandler"},{"Time":0.6649,"Method":"OnUse","Class":"SCPStats.EventHandler"},{"Time":0.0198,"Method":"OnInteractingDoor","Class":"DiscordIntegration.Events.PlayerHandler"},{"Time":0.0117,"Method":"OnDoorOpen","Class":"AdminTools.EventHandlers"},{"Time":0.0078000000000000005,"Method":"OnPlayerInteractingDoor","Class":"AdminTools.EventHandlers"},{"Time":0.012,"Method":"OnInteractingDoor","Class":"Common_Utilities.EventHandlers.PlayerHandlers"},{"Time":0.0334,"Method":"OnDoorInteract","Class":"RemoteKeycard.EventsHandler"},{"Time":0.0235,"Method":"OnInteractingDoor","Class":"FbiOpenUp.EventHandlers"},{"Time":0.015300000000000001,"Method":"AntiAfkEventHandler","Class":"Common_Utilities.EventHandlers.PlayerHandlers"},{"Time":0.0233,"Method":"OnChangingItem","Class":"DiscordIntegration.Events.PlayerHandler"},{"Time":0.0362,"Method":"AntiAfkEventHandler","Class":"Common_Utilities.EventHandlers.PlayerHandlers"},{"Time":0.0201,"Method":"AntiAfkEventHandler","Class":"Common_Utilities.EventHandlers.PlayerHandlers"},{"Time":0.0205,"Method":"AntiAfkEventHandler","Class":"Common_Utilities.EventHandlers.PlayerHandlers"},{"Time":0.0194,"Method":"AntiAfkEventHandler","Class":"Common_Utilities.EventHandlers.PlayerHandlers"},{"Time":0.016800000000000002,"Method":"OnRoundEnding","Class":"SCPStats.EventHandler"},{"Time":0.0164,"Method":"AntiAfkEventHandler","Class":"Common_Utilities.EventHandlers.PlayerHandlers"},{"Time":0.0189,"Method":"AntiAfkEventHandler","Class":"Common_Utilities.EventHandlers.PlayerHandlers"},{"Time":0.0179,"Method":"AntiAfkEventHandler","Class":"Common_Utilities.EventHandlers.PlayerHandlers"},{"Time":0.0188,"Method":"AntiAfkEventHandler","Class":"Common_Utilities.EventHandlers.PlayerHandlers"},{"Time":0.025900000000000003,"Method":"OnInteractingDoor","Class":"DiscordIntegration.Events.PlayerHandler"},{"Time":0.014400000000000001,"Method":"OnDoorOpen","Class":"AdminTools.EventHandlers"},{"Time":0.0111,"Method":"OnPlayerInteractingDoor","Class":"AdminTools.EventHandlers"},{"Time":0.0134,"Method":"OnInteractingDoor","Class":"Common_Utilities.EventHandlers.PlayerHandlers"},{"Time":0.1073,"Method":"OnDoorInteract","Class":"RemoteKeycard.EventsHandler"},{"Time":0.0258,"Method":"OnInteractingDoor","Class":"FbiOpenUp.EventHandlers"},{"Time":0.0286,"Method":"OnInteractingDoor","Class":"DiscordIntegration.Events.PlayerHandler"},{"Time":0.013300000000000001,"Method":"OnDoorOpen","Class":"AdminTools.EventHandlers"},{"Time":0.0103,"Method":"OnPlayerInteractingDoor","Class":"AdminTools.EventHandlers"},{"Time":0.0155,"Method":"OnInteractingDoor","Class":"Common_Utilities.EventHandlers.PlayerHandlers"},{"Time":0.1022,"Method":"OnDoorInteract","Class":"RemoteKeycard.EventsHandler"},{"Time":0.027,"Method":"OnInteractingDoor","Class":"FbiOpenUp.EventHandlers"},{"Time":0.0178,"Method":"AntiAfkEventHandler","Class":"Common_Utilities.EventHandlers.PlayerHandlers"},{"Time":0.0182,"Method":"AntiAfkEventHandler","Class":"Common_Utilities.EventHandlers.PlayerHandlers"},{"Time":0.024300000000000002,"Method":"OnInteractingDoor","Class":"DiscordIntegration.Events.PlayerHandler"},{"Time":0.0103,"Method":"OnDoorOpen","Class":"AdminTools.EventHandlers"},{"Time":0.0075000000000000006,"Method":"OnPlayerInteractingDoor","Class":"AdminTools.EventHandlers"},{"Time":0.0103,"Method":"OnInteractingDoor","Class":"Common_Utilities.EventHandlers.PlayerHandlers"},{"Time":0.1015,"Method":"OnDoorInteract","Class":"RemoteKeycard.EventsHandler"},{"Time":0.023700000000000002,"Method":"OnInteractingDoor","Class":"FbiOpenUp.EventHandlers"},{"Time":0.019700000000000002,"Method":"AntiAfkEventHandler","Class":"Common_Utilities.EventHandlers.PlayerHandlers"},{"Time":0.0198,"Method":"OnRoundEnding","Class":"SCPStats.EventHandler"},{"Time":0.015700000000000002,"Method":"AntiAfkEventHandler","Class":"Common_Utilities.EventHandlers.PlayerHandlers"},{"Time":0.022000000000000002,"Method":"AntiAfkEventHandler","Class":"Common_Utilities.EventHandlers.PlayerHandlers"},{"Time":0.016900000000000002,"Method":"AntiAfkEventHandler","Class":"Common_Utilities.EventHandlers.PlayerHandlers"},{"Time":0.0145,"Method":"AntiAfkEventHandler","Class":"Common_Utilities.EventHandlers.PlayerHandlers"},{"Time":0.0159,"Method":"AntiAfkEventHandler","Class":"Common_Utilities.EventHandlers.PlayerHandlers"},{"Time":0.0274,"Method":"AntiAfkEventHandler","Class":"Common_Utilities.EventHandlers.PlayerHandlers"},{"Time":0.018600000000000002,"Method":"AntiAfkEventHandler","Class":"Common_Utilities.EventHandlers.PlayerHandlers"},{"Time":0.0146,"Method":"AntiAfkEventHandler","Class":"Common_Utilities.EventHandlers.PlayerHandlers"},{"Time":0.0274,"Method":"OnInteractingDoor","Class":"DiscordIntegration.Events.PlayerHandler"},{"Time":0.0222,"Method":"OnDoorOpen","Class":"AdminTools.EventHandlers"},{"Time":0.0159,"Method":"OnPlayerInteractingDoor","Class":"AdminTools.EventHandlers"},{"Time":0.0449,"Method":"OnInteractingDoor","Class":"Common_Utilities.EventHandlers.PlayerHandlers"},{"Time":0.1359,"Method":"OnDoorInteract","Class":"RemoteKeycard.EventsHandler"},{"Time":0.030600000000000002,"Method":"OnInteractingDoor","Class":"FbiOpenUp.EventHandlers"},{"Time":0.0154,"Method":"AntiAfkEventHandler","Class":"Common_Utilities.EventHandlers.PlayerHandlers"},{"Time":0.0308,"Method":"OnInteractingDoor","Class":"DiscordIntegration.Events.PlayerHandler"},{"Time":0.015700000000000002,"Method":"OnDoorOpen","Class":"AdminTools.EventHandlers"},{"Time":0.0236,"Method":"OnPlayerInteractingDoor","Class":"AdminTools.EventHandlers"},{"Time":0.023,"Method":"OnInteractingDoor","Class":"Common_Utilities.EventHandlers.PlayerHandlers"},{"Time":0.1268,"Method":"OnDoorInteract","Class":"RemoteKeycard.EventsHandler"},{"Time":0.0502,"Method":"OnInteractingDoor","Class":"FbiOpenUp.EventHandlers"},{"Time":0.0207,"Method":"AntiAfkEventHandler","Class":"Common_Utilities.EventHandlers.PlayerHandlers"},{"Time":0.057800000000000004,"Method":"OnRoundEnding","Class":"SCPStats.EventHandler"},{"Time":0.012100000000000001,"Method":"AntiAfkEventHandler","Class":"Common_Utilities.EventHandlers.PlayerHandlers"},{"Time":0.0224,"Method":"OnInteractingDoor","Class":"DiscordIntegration.Events.PlayerHandler"},{"Time":0.010700000000000001,"Method":"OnDoorOpen","Class":"AdminTools.EventHandlers"},{"Time":0.007,"Method":"OnPlayerInteractingDoor","Class":"AdminTools.EventHandlers"},{"Time":0.0126,"Method":"OnInteractingDoor","Class":"Common_Utilities.EventHandlers.PlayerHandlers"},{"Time":0.0903,"Method":"OnDoorInteract","Class":"RemoteKeycard.EventsHandler"},{"Time":0.0219,"Method":"OnInteractingDoor","Class":"FbiOpenUp.EventHandlers"},{"Time":0.0161,"Method":"AntiAfkEventHandler","Class":"Common_Utilities.EventHandlers.PlayerHandlers"},{"Time":0.0246,"Method":"AntiAfkEventHandler","Class":"Common_Utilities.EventHandlers.PlayerHandlers"},{"Time":0.0224,"Method":"AntiAfkEventHandler","Class":"Common_Utilities.EventHandlers.PlayerHandlers"},{"Time":0.014700000000000001,"Method":"AntiAfkEventHandler","Class":"Common_Utilities.EventHandlers.PlayerHandlers"},{"Time":0.0181,"Method":"AntiAfkEventHandler","Class":"Common_Utilities.EventHandlers.PlayerHandlers"},{"Time":0.015000000000000001,"Method":"AntiAfkEventHandler","Class":"Common_Utilities.EventHandlers.PlayerHandlers"},{"Time":0.019700000000000002,"Method":"AntiAfkEventHandler","Class":"Common_Utilities.EventHandlers.PlayerHandlers"},{"Time":0.0257,"Method":"OnRoundEnding","Class":"SCPStats.EventHandler"},{"Time":0.0183,"Method":"AntiAfkEventHandler","Class":"Common_Utilities.EventHandlers.PlayerHandlers"},{"Time":0.0414,"Method":"OnInteractingDoor","Class":"DiscordIntegration.Events.PlayerHandler"},{"Time":0.0448,"Method":"OnDoorOpen","Class":"AdminTools.EventHandlers"},{"Time":0.014100000000000001,"Method":"OnPlayerInteractingDoor","Class":"AdminTools.EventHandlers"},{"Time":0.025,"Method":"OnInteractingDoor","Class":"Common_Utilities.EventHandlers.PlayerHandlers"},{"Time":0.3164,"Method":"OnDoorInteract","Class":"RemoteKeycard.EventsHandler"},{"Time":0.0555,"Method":"OnInteractingDoor","Class":"FbiOpenUp.EventHandlers"},{"Time":0.013800000000000002,"Method":"AntiAfkEventHandler","Class":"Common_Utilities.EventHandlers.PlayerHandlers"},{"Time":0.0152,"Method":"AntiAfkEventHandler","Class":"Common_Utilities.EventHandlers.PlayerHandlers"},{"Time":0.0172,"Method":"OnInteractingDoor","Class":"DiscordIntegration.Events.PlayerHandler"},{"Time":0.0109,"Method":"OnDoorOpen","Class":"AdminTools.EventHandlers"},{"Time":0.0074,"Method":"OnPlayerInteractingDoor","Class":"AdminTools.EventHandlers"},{"Time":0.0102,"Method":"OnInteractingDoor","Class":"Common_Utilities.EventHandlers.PlayerHandlers"},{"Time":0.11420000000000001,"Method":"OnDoorInteract","Class":"RemoteKeycard.EventsHandler"},{"Time":0.023,"Method":"OnInteractingDoor","Class":"FbiOpenUp.EventHandlers"},{"Time":0.020800000000000003,"Method":"AntiAfkEventHandler","Class":"Common_Utilities.EventHandlers.PlayerHandlers"},{"Time":0.0205,"Method":"AntiAfkEventHandler","Class":"Common_Utilities.EventHandlers.PlayerHandlers"},{"Time":0.0198,"Method":"AntiAfkEventHandler","Class":"Common_Utilities.EventHandlers.PlayerHandlers"},{"Time":0.0054,"Method":"AntiAfkEventHandler","Class":"Common_Utilities.EventHandlers.PlayerHandlers"},{"Time":0.018000000000000002,"Method":"AntiAfkEventHandler","Class":"Common_Utilities.EventHandlers.PlayerHandlers"},{"Time":0.0158,"Method":"AntiAfkEventHandler","Class":"Common_Utilities.EventHandlers.PlayerHandlers"},{"Time":0.019100000000000002,"Method":"AntiAfkEventHandler","Class":"Common_Utilities.EventHandlers.PlayerHandlers"},{"Time":0.021500000000000002,"Method":"AntiAfkEventHandler","Class":"Common_Utilities.EventHandlers.PlayerHandlers"},{"Time":0.0152,"Method":"AntiAfkEventHandler","Class":"Common_Utilities.EventHandlers.PlayerHandlers"},{"Time":0.0165,"Method":"AntiAfkEventHandler","Class":"Common_Utilities.EventHandlers.PlayerHandlers"},{"Time":0.020200000000000003,"Method":"AntiAfkEventHandler","Class":"Common_Utilities.EventHandlers.PlayerHandlers"},{"Time":0.0241,"Method":"OnRoundEnding","Class":"SCPStats.EventHandler"},{"Time":0.018500000000000003,"Method":"AntiAfkEventHandler","Class":"Common_Utilities.EventHandlers.PlayerHandlers"},{"Time":0.0193,"Method":"AntiAfkEventHandler","Class":"Common_Utilities.EventHandlers.PlayerHandlers"},{"Time":0.0199,"Method":"AntiAfkEventHandler","Class":"Common_Utilities.EventHandlers.PlayerHandlers"},{"Time":0.0151,"Method":"AntiAfkEventHandler","Class":"Common_Utilities.EventHandlers.PlayerHandlers"},{"Time":0.0284,"Method":"OnInteractingDoor","Class":"DiscordIntegration.Events.PlayerHandler"},{"Time":0.0291,"Method":"OnDoorOpen","Class":"AdminTools.EventHandlers"},{"Time":0.0173,"Method":"OnPlayerInteractingDoor","Class":"AdminTools.EventHandlers"},{"Time":0.015600000000000001,"Method":"OnInteractingDoor","Class":"Common_Utilities.EventHandlers.PlayerHandlers"},{"Time":0.14730000000000001,"Method":"OnDoorInteract","Class":"RemoteKeycard.EventsHandler"},{"Time":0.0349,"Method":"OnInteractingDoor","Class":"FbiOpenUp.EventHandlers"},{"Time":0.0145,"Method":"AntiAfkEventHandler","Class":"Common_Utilities.EventHandlers.PlayerHandlers"},{"Time":0.026600000000000002,"Method":"OnInteractingDoor","Class":"DiscordIntegration.Events.PlayerHandler"},{"Time":0.0106,"Method":"OnDoorOpen","Class":"AdminTools.EventHandlers"},{"Time":0.0078000000000000005,"Method":"OnPlayerInteractingDoor","Class":"AdminTools.EventHandlers"},{"Time":0.0118,"Method":"OnInteractingDoor","Class":"Common_Utilities.EventHandlers.PlayerHandlers"},{"Time":0.0927,"Method":"OnDoorInteract","Class":"RemoteKeycard.EventsHandler"},{"Time":0.0221,"Method":"OnInteractingDoor","Class":"FbiOpenUp.EventHandlers"},{"Time":0.0162,"Method":"AntiAfkEventHandler","Class":"Common_Utilities.EventHandlers.PlayerHandlers"},{"Time":0.0154,"Method":"AntiAfkEventHandler","Class":"Common_Utilities.EventHandlers.PlayerHandlers"},{"Time":0.0218,"Method":"OnInteractingDoor","Class":"DiscordIntegration.Events.PlayerHandler"},{"Time":0.011300000000000001,"Method":"OnDoorOpen","Class":"AdminTools.EventHandlers"},{"Time":0.008,"Method":"OnPlayerInteractingDoor","Class":"AdminTools.EventHandlers"},{"Time":0.012400000000000001,"Method":"OnInteractingDoor","Class":"Common_Utilities.EventHandlers.PlayerHandlers"},{"Time":0.08900000000000001,"Method":"OnDoorInteract","Class":"RemoteKeycard.EventsHandler"},{"Time":0.021400000000000002,"Method":"OnInteractingDoor","Class":"FbiOpenUp.EventHandlers"},{"Time":0.0166,"Method":"AntiAfkEventHandler","Class":"Common_Utilities.EventHandlers.PlayerHandlers"},{"Time":0.016800000000000002,"Method":"AntiAfkEventHandler","Class":"Common_Utilities.EventHandlers.PlayerHandlers"},{"Time":0.0198,"Method":"OnRoundEnding","Class":"SCPStats.EventHandler"},{"Time":0.0161,"Method":"AntiAfkEventHandler","Class":"Common_Utilities.EventHandlers.PlayerHandlers"},{"Time":0.0235,"Method":"AntiAfkEventHandler","Class":"Common_Utilities.EventHandlers.PlayerHandlers"},{"Time":0.0176,"Method":"AntiAfkEventHandler","Class":"Common_Utilities.EventHandlers.PlayerHandlers"},{"Time":0.0146,"Method":"AntiAfkEventHandler","Class":"Common_Utilities.EventHandlers.PlayerHandlers"},{"Time":0.0548,"Method":"AntiAfkEventHandler","Class":"Common_Utilities.EventHandlers.PlayerHandlers"},{"Time":0.12140000000000001,"Method":"OnInteractingDoor","Class":"DiscordIntegration.Events.PlayerHandler"},{"Time":0.0187,"Method":"OnDoorOpen","Class":"AdminTools.EventHandlers"},{"Time":0.011300000000000001,"Method":"OnPlayerInteractingDoor","Class":"AdminTools.EventHandlers"},{"Time":0.0193,"Method":"OnInteractingDoor","Class":"Common_Utilities.EventHandlers.PlayerHandlers"},{"Time":0.1424,"Method":"OnDoorInteract","Class":"RemoteKeycard.EventsHandler"},{"Time":0.0364,"Method":"OnInteractingDoor","Class":"FbiOpenUp.EventHandlers"},{"Time":0.0161,"Method":"AntiAfkEventHandler","Class":"Common_Utilities.EventHandlers.PlayerHandlers"},{"Time":0.0258,"Method":"OnInteractingDoor","Class":"DiscordIntegration.Events.PlayerHandler"},{"Time":0.0126,"Method":"OnDoorOpen","Class":"AdminTools.EventHandlers"},{"Time":0.0096000000000000009,"Method":"OnPlayerInteractingDoor","Class":"AdminTools.EventHandlers"},{"Time":0.0137,"Method":"OnInteractingDoor","Class":"Common_Utilities.EventHandlers.PlayerHandlers"},{"Time":0.1236,"Method":"OnDoorInteract","Class":"RemoteKeycard.EventsHandler"},{"Time":0.0291,"Method":"OnInteractingDoor","Class":"FbiOpenUp.EventHandlers"},{"Time":0.015600000000000001,"Method":"AntiAfkEventHandler","Class":"Common_Utilities.EventHandlers.PlayerHandlers"},{"Time":0.025,"Method":"OnRoundEnding","Class":"SCPStats.EventHandler"},{"Time":0.020300000000000002,"Method":"AntiAfkEventHandler","Class":"Common_Utilities.EventHandlers.PlayerHandlers"},{"Time":0.0123,"Method":"AntiAfkEventHandler","Class":"Common_Utilities.EventHandlers.PlayerHandlers"},{"Time":0.0146,"Method":"AntiAfkEventHandler","Class":"Common_Utilities.EventHandlers.PlayerHandlers"},{"Time":0.0171,"Method":"AntiAfkEventHandler","Class":"Common_Utilities.EventHandlers.PlayerHandlers"},{"Time":0.015000000000000001,"Method":"AntiAfkEventHandler","Class":"Common_Utilities.EventHandlers.PlayerHandlers"},{"Time":0.0178,"Method":"AntiAfkEventHandler","Class":"Common_Utilities.EventHandlers.PlayerHandlers"},{"Time":0.017,"Method":"AntiAfkEventHandler","Class":"Common_Utilities.EventHandlers.PlayerHandlers"},{"Time":0.0201,"Method":"AntiAfkEventHandler","Class":"Common_Utilities.EventHandlers.PlayerHandlers"},{"Time":0.0286,"Method":"OnRoundEnding","Class":"SCPStats.EventHandler"},{"Time":0.029500000000000002,"Method":"OnInteractingDoor","Class":"DiscordIntegration.Events.PlayerHandler"},{"Time":0.0167,"Method":"OnDoorOpen","Class":"AdminTools.EventHandlers"},{"Time":0.0088,"Method":"OnPlayerInteractingDoor","Class":"AdminTools.EventHandlers"},{"Time":0.0165,"Method":"OnInteractingDoor","Class":"Common_Utilities.EventHandlers.PlayerHandlers"},{"Time":0.21080000000000002,"Method":"OnDoorInteract","Class":"RemoteKeycard.EventsHandler"},{"Time":0.043300000000000005,"Method":"OnInteractingDoor","Class":"FbiOpenUp.EventHandlers"},{"Time":0.015300000000000001,"Method":"AntiAfkEventHandler","Class":"Common_Utilities.EventHandlers.PlayerHandlers"},{"Time":0.024800000000000003,"Method":"OnInteractingDoor","Class":"DiscordIntegration.Events.PlayerHandler"},{"Time":0.0115,"Method":"OnDoorOpen","Class":"AdminTools.EventHandlers"},{"Time":0.0077,"Method":"OnPlayerInteractingDoor","Class":"AdminTools.EventHandlers"},{"Time":0.0123,"Method":"OnInteractingDoor","Class":"Common_Utilities.EventHandlers.PlayerHandlers"},{"Time":0.0998,"Method":"OnDoorInteract","Class":"RemoteKeycard.EventsHandler"},{"Time":0.0252,"Method":"OnInteractingDoor","Class":"FbiOpenUp.EventHandlers"},{"Time":0.016300000000000002,"Method":"AntiAfkEventHandler","Class":"Common_Utilities.EventHandlers.PlayerHandlers"},{"Time":0.0216,"Method":"AntiAfkEventHandler","Class":"Common_Utilities.EventHandlers.PlayerHandlers"},{"Time":0.0162,"Method":"AntiAfkEventHandler","Class":"Common_Utilities.EventHandlers.PlayerHandlers"},{"Time":0.0193,"Method":"AntiAfkEventHandler","Class":"Common_Utilities.EventHandlers.PlayerHandlers"},{"Time":0.0176,"Method":"AntiAfkEventHandler","Class":"Common_Utilities.EventHandlers.PlayerHandlers"},{"Time":0.038700000000000005,"Method":"OnInteractingDoor","Class":"DiscordIntegration.Events.PlayerHandler"},{"Time":0.0154,"Method":"OnDoorOpen","Class":"AdminTools.EventHandlers"},{"Time":0.0095,"Method":"OnPlayerInteractingDoor","Class":"AdminTools.EventHandlers"},{"Time":0.0187,"Method":"OnInteractingDoor","Class":"Common_Utilities.EventHandlers.PlayerHandlers"},{"Time":0.124,"Method":"OnDoorInteract","Class":"RemoteKeycard.EventsHandler"},{"Time":0.0344,"Method":"OnInteractingDoor","Class":"FbiOpenUp.EventHandlers"},{"Time":0.0302,"Method":"AntiAfkEventHandler","Class":"Common_Utilities.EventHandlers.PlayerHandlers"},{"Time":0.0221,"Method":"AntiAfkEventHandler","Class":"Common_Utilities.EventHandlers.PlayerHandlers"},{"Time":0.0273,"Method":"OnInteractingDoor","Class":"DiscordIntegration.Events.PlayerHandler"},{"Time":0.0142,"Method":"OnDoorOpen","Class":"AdminTools.EventHandlers"},{"Time":0.0108,"Method":"OnPlayerInteractingDoor","Class":"AdminTools.EventHandlers"},{"Time":0.014700000000000001,"Method":"OnInteractingDoor","Class":"Common_Utilities.EventHandlers.PlayerHandlers"},{"Time":0.12490000000000001,"Method":"OnDoorInteract","Class":"RemoteKeycard.EventsHandler"},{"Time":0.0267,"Method":"OnInteractingDoor","Class":"FbiOpenUp.EventHandlers"},{"Time":0.0176,"Method":"AntiAfkEventHandler","Class":"Common_Utilities.EventHandlers.PlayerHandlers"},{"Time":0.0161,"Method":"OnRoundEnding","Class":"SCPStats.EventHandler"},{"Time":0.020300000000000002,"Method":"AntiAfkEventHandler","Class":"Common_Utilities.EventHandlers.PlayerHandlers"},{"Time":0.0149,"Method":"AntiAfkEventHandler","Class":"Common_Utilities.EventHandlers.PlayerHandlers"},{"Time":0.0167,"Method":"AntiAfkEventHandler","Class":"Common_Utilities.EventHandlers.PlayerHandlers"},{"Time":0.018500000000000003,"Method":"AntiAfkEventHandler","Class":"Common_Utilities.EventHandlers.PlayerHandlers"},{"Time":0.0161,"Method":"AntiAfkEventHandler","Class":"Common_Utilities.EventHandlers.PlayerHandlers"},{"Time":0.0179,"Method":"AntiAfkEventHandler","Class":"Common_Utilities.EventHandlers.PlayerHandlers"},{"Time":0.0207,"Method":"AntiAfkEventHandler","Class":"Common_Utilities.EventHandlers.PlayerHandlers"},{"Time":0.0184,"Method":"AntiAfkEventHandler","Class":"Common_Utilities.EventHandlers.PlayerHandlers"},{"Time":0.0151,"Method":"AntiAfkEventHandler","Class":"Common_Utilities.EventHandlers.PlayerHandlers"},{"Time":0.0194,"Method":"AntiAfkEventHandler","Class":"Common_Utilities.EventHandlers.PlayerHandlers"},{"Time":0.0218,"Method":"AntiAfkEventHandler","Class":"Common_Utilities.EventHandlers.PlayerHandlers"},{"Time":0.48950000000000005,"Method":"OnInteractingLocker","Class":"DiscordIntegration.Events.PlayerHandler"},{"Time":0.0839,"Method":"OnLockerInteract","Class":"RemoteKeycard.EventsHandler"},{"Time":1.8413000000000002,"Method":"OnInteractingLocker","Class":"DiscordIntegration.Events.PlayerHandler"},{"Time":0.0437,"Method":"OnLockerInteract","Class":"RemoteKeycard.EventsHandler"},{"Time":0.18730000000000002,"Method":"OnInteractingLocker","Class":"DiscordIntegration.Events.PlayerHandler"},{"Time":0.0373,"Method":"OnLockerInteract","Class":"RemoteKeycard.EventsHandler"},{"Time":0.0188,"Method":"OnRoundEnding","Class":"SCPStats.EventHandler"},{"Time":0.0775,"Method":"OnPickingUpItem","Class":"DiscordIntegration.Events.PlayerHandler"},{"Time":0.3356,"Method":"OnPickup","Class":"SCPStats.EventHandler"},{"Time":0.025900000000000003,"Method":"OnRoundEnding","Class":"SCPStats.EventHandler"},{"Time":0.030100000000000002,"Method":"OnPickingUpItem","Class":"DiscordIntegration.Events.PlayerHandler"},{"Time":0.5112,"Method":"OnPickup","Class":"SCPStats.EventHandler"},{"Time":0.0269,"Method":"AntiAfkEventHandler","Class":"Common_Utilities.EventHandlers.PlayerHandlers"},{"Time":0.0162,"Method":"AntiAfkEventHandler","Class":"Common_Utilities.EventHandlers.PlayerHandlers"},{"Time":0.0172,"Method":"AntiAfkEventHandler","Class":"Common_Utilities.EventHandlers.PlayerHandlers"},{"Time":0.0135,"Method":"AntiAfkEventHandler","Class":"Common_Utilities.EventHandlers.PlayerHandlers"},{"Time":0.0217,"Method":"AntiAfkEventHandler","Class":"Common_Utilities.EventHandlers.PlayerHandlers"},{"Time":0.0284,"Method":"AntiAfkEventHandler","Class":"Common_Utilities.EventHandlers.PlayerHandlers"},{"Time":0.016800000000000002,"Method":"AntiAfkEventHandler","Class":"Common_Utilities.EventHandlers.PlayerHandlers"},{"Time":0.0284,"Method":"AntiAfkEventHandler","Class":"Common_Utilities.EventHandlers.PlayerHandlers"},{"Time":0.0097,"Method":"AntiAfkEventHandler","Class":"Common_Utilities.EventHandlers.PlayerHandlers"},{"Time":0.042800000000000005,"Method":"OnPickingUpItem","Class":"DiscordIntegration.Events.PlayerHandler"},{"Time":0.1421,"Method":"OnPickup","Class":"SCPStats.EventHandler"},{"Time":0.0159,"Method":"OnRoundEnding","Class":"SCPStats.EventHandler"},{"Time":0.015000000000000001,"Method":"AntiAfkEventHandler","Class":"Common_Utilities.EventHandlers.PlayerHandlers"},{"Time":0.017400000000000002,"Method":"AntiAfkEventHandler","Class":"Common_Utilities.EventHandlers.PlayerHandlers"},{"Time":0.0173,"Method":"AntiAfkEventHandler","Class":"Common_Utilities.EventHandlers.PlayerHandlers"},{"Time":0.0216,"Method":"AntiAfkEventHandler","Class":"Common_Utilities.EventHandlers.PlayerHandlers"},{"Time":0.016300000000000002,"Method":"AntiAfkEventHandler","Class":"Common_Utilities.EventHandlers.PlayerHandlers"},{"Time":0.015600000000000001,"Method":"AntiAfkEventHandler","Class":"Common_Utilities.EventHandlers.PlayerHandlers"},{"Time":0.0106,"Method":"AntiAfkEventHandler","Class":"Common_Utilities.EventHandlers.PlayerHandlers"},{"Time":0.0205,"Method":"AntiAfkEventHandler","Class":"Common_Utilities.EventHandlers.PlayerHandlers"},{"Time":0.06770000000000001,"Method":"AntiAfkEventHandler","Class":"Common_Utilities.EventHandlers.PlayerHandlers"},{"Time":0.018500000000000003,"Method":"AntiAfkEventHandler","Class":"Common_Utilities.EventHandlers.PlayerHandlers"},{"Time":0.017,"Method":"AntiAfkEventHandler","Class":"Common_Utilities.EventHandlers.PlayerHandlers"},{"Time":0.020300000000000002,"Method":"AntiAfkEventHandler","Class":"Common_Utilities.EventHandlers.PlayerHandlers"},{"Time":0.0303,"Method":"AntiAfkEventHandler","Class":"Common_Utilities.EventHandlers.PlayerHandlers"},{"Time":0.0178,"Method":"AntiAfkEventHandler","Class":"Common_Utilities.EventHandlers.PlayerHandlers"},{"Time":0.019,"Method":"OnRoundEnding","Class":"SCPStats.EventHandler"},{"Time":0.0212,"Method":"AntiAfkEventHandler","Class":"Common_Utilities.EventHandlers.PlayerHandlers"},{"Time":0.0173,"Method":"AntiAfkEventHandler","Class":"Common_Utilities.EventHandlers.PlayerHandlers"},{"Time":0.0189,"Method":"AntiAfkEventHandler","Class":"Common_Utilities.EventHandlers.PlayerHandlers"},{"Time":0.0216,"Method":"AntiAfkEventHandler","Class":"Common_Utilities.EventHandlers.PlayerHandlers"},{"Time":0.0148,"Method":"AntiAfkEventHandler","Class":"Common_Utilities.EventHandlers.PlayerHandlers"},{"Time":0.0188,"Method":"AntiAfkEventHandler","Class":"Common_Utilities.EventHandlers.PlayerHandlers"},{"Time":0.021400000000000002,"Method":"AntiAfkEventHandler","Class":"Common_Utilities.EventHandlers.PlayerHandlers"},{"Time":0.0239,"Method":"AntiAfkEventHandler","Class":"Common_Utilities.EventHandlers.PlayerHandlers"},{"Time":0.0165,"Method":"AntiAfkEventHandler","Class":"Common_Utilities.EventHandlers.PlayerHandlers"},{"Time":0.0205,"Method":"AntiAfkEventHandler","Class":"Common_Utilities.EventHandlers.PlayerHandlers"},{"Time":0.0216,"Method":"AntiAfkEventHandler","Class":"Common_Utilities.EventHandlers.PlayerHandlers"},{"Time":0.016,"Method":"AntiAfkEventHandler","Class":"Common_Utilities.EventHandlers.PlayerHandlers"},{"Time":0.0155,"Method":"AntiAfkEventHandler","Class":"Common_Utilities.EventHandlers.PlayerHandlers"},{"Time":0.0184,"Method":"AntiAfkEventHandler","Class":"Common_Utilities.EventHandlers.PlayerHandlers"},{"Time":0.013800000000000002,"Method":"AntiAfkEventHandler","Class":"Common_Utilities.EventHandlers.PlayerHandlers"},{"Time":0.019700000000000002,"Method":"AntiAfkEventHandler","Class":"Common_Utilities.EventHandlers.PlayerHandlers"},{"Time":0.0218,"Method":"AntiAfkEventHandler","Class":"Common_Utilities.EventHandlers.PlayerHandlers"},{"Time":0.019,"Method":"AntiAfkEventHandler","Class":"Common_Utilities.EventHandlers.PlayerHandlers"},{"Time":0.0158,"Method":"OnRoundEnding","Class":"SCPStats.EventHandler"},{"Time":0.0173,"Method":"AntiAfkEventHandler","Class":"Common_Utilities.EventHandlers.PlayerHandlers"},{"Time":0.018500000000000003,"Method":"AntiAfkEventHandler","Class":"Common_Utilities.EventHandlers.PlayerHandlers"},{"Time":0.0148,"Method":"AntiAfkEventHandler","Class":"Common_Utilities.EventHandlers.PlayerHandlers"},{"Time":0.0194,"Method":"AntiAfkEventHandler","Class":"Common_Utilities.EventHandlers.PlayerHandlers"},{"Time":0.017,"Method":"AntiAfkEventHandler","Class":"Common_Utilities.EventHandlers.PlayerHandlers"},{"Time":0.0195,"Method":"AntiAfkEventHandler","Class":"Common_Utilities.EventHandlers.PlayerHandlers"},{"Time":0.0221,"Method":"AntiAfkEventHandler","Class":"Common_Utilities.EventHandlers.PlayerHandlers"},{"Time":0.0219,"Method":"AntiAfkEventHandler","Class":"Common_Utilities.EventHandlers.PlayerHandlers"},{"Time":0.016,"Method":"AntiAfkEventHandler","Class":"Common_Utilities.EventHandlers.PlayerHandlers"},{"Time":0.019100000000000002,"Method":"AntiAfkEventHandler","Class":"Common_Utilities.EventHandlers.PlayerHandlers"},{"Time":0.0152,"Method":"AntiAfkEventHandler","Class":"Common_Utilities.EventHandlers.PlayerHandlers"},{"Time":0.0182,"Method":"AntiAfkEventHandler","Class":"Common_Utilities.EventHandlers.PlayerHandlers"},{"Time":0.0126,"Method":"AntiAfkEventHandler","Class":"Common_Utilities.EventHandlers.PlayerHandlers"},{"Time":0.028800000000000003,"Method":"OnRoundEnding","Class":"SCPStats.EventHandler"},{"Time":0.020900000000000002,"Method":"AntiAfkEventHandler","Class":"Common_Utilities.EventHandlers.PlayerHandlers"},{"Time":0.156,"Method":"AntiAfkEventHandler","Class":"Common_Utilities.EventHandlers.PlayerHandlers"},{"Time":0.038900000000000004,"Method":"OnChangingItem","Class":"DiscordIntegration.Events.PlayerHandler"},{"Time":0.0154,"Method":"AntiAfkEventHandler","Class":"Common_Utilities.EventHandlers.PlayerHandlers"},{"Time":0.0172,"Method":"AntiAfkEventHandler","Class":"Common_Utilities.EventHandlers.PlayerHandlers"},{"Time":0.016,"Method":"AntiAfkEventHandler","Class":"Common_Utilities.EventHandlers.PlayerHandlers"},{"Time":0.0171,"Method":"AntiAfkEventHandler","Class":"Common_Utilities.EventHandlers.PlayerHandlers"},{"Time":0.0159,"Method":"AntiAfkEventHandler","Class":"Common_Utilities.EventHandlers.PlayerHandlers"},{"Time":0.0438,"Method":"OnInteractingDoor","Class":"DiscordIntegration.Events.PlayerHandler"},{"Time":0.029400000000000003,"Method":"OnDoorOpen","Class":"AdminTools.EventHandlers"},{"Time":0.0187,"Method":"OnPlayerInteractingDoor","Class":"AdminTools.EventHandlers"},{"Time":0.018600000000000002,"Method":"OnInteractingDoor","Class":"Common_Utilities.EventHandlers.PlayerHandlers"},{"Time":1.3613,"Method":"OnDoorInteract","Class":"RemoteKeycard.EventsHandler"},{"Time":0.087500000000000008,"Method":"OnInteractingDoor","Class":"FbiOpenUp.EventHandlers"},{"Time":0.045200000000000004,"Method":"AntiAfkEventHandler","Class":"Common_Utilities.EventHandlers.PlayerHandlers"},{"Time":0.016,"Method":"AntiAfkEventHandler","Class":"Common_Utilities.EventHandlers.PlayerHandlers"},{"Time":0.0235,"Method":"OnInteractingDoor","Class":"DiscordIntegration.Events.PlayerHandler"},{"Time":0.0112,"Method":"OnDoorOpen","Class":"AdminTools.EventHandlers"},{"Time":0.0076,"Method":"OnPlayerInteractingDoor","Class":"AdminTools.EventHandlers"},{"Time":0.011300000000000001,"Method":"OnInteractingDoor","Class":"Common_Utilities.EventHandlers.PlayerHandlers"},{"Time":0.082,"Method":"OnDoorInteract","Class":"RemoteKeycard.EventsHandler"},{"Time":0.025500000000000002,"Method":"OnInteractingDoor","Class":"FbiOpenUp.EventHandlers"},{"Time":0.021500000000000002,"Method":"AntiAfkEventHandler","Class":"Common_Utilities.EventHandlers.PlayerHandlers"},{"Time":0.0148,"Method":"AntiAfkEventHandler","Class":"Common_Utilities.EventHandlers.PlayerHandlers"},{"Time":0.0162,"Method":"AntiAfkEventHandler","Class":"Common_Utilities.EventHandlers.PlayerHandlers"},{"Time":0.018500000000000003,"Method":"AntiAfkEventHandler","Class":"Common_Utilities.EventHandlers.PlayerHandlers"},{"Time":0.0131,"Method":"AntiAfkEventHandler","Class":"Common_Utilities.EventHandlers.PlayerHandlers"},{"Time":0.0166,"Method":"OnRoundEnding","Class":"SCPStats.EventHandler"},{"Time":0.0155,"Method":"AntiAfkEventHandler","Class":"Common_Utilities.EventHandlers.PlayerHandlers"},{"Time":0.0166,"Method":"AntiAfkEventHandler","Class":"Common_Utilities.EventHandlers.PlayerHandlers"},{"Time":0.0161,"Method":"AntiAfkEventHandler","Class":"Common_Utilities.EventHandlers.PlayerHandlers"},{"Time":0.02,"Method":"AntiAfkEventHandler","Class":"Common_Utilities.EventHandlers.PlayerHandlers"},{"Time":0.027100000000000003,"Method":"OnInteractingDoor","Class":"DiscordIntegration.Events.PlayerHandler"},{"Time":0.0131,"Method":"OnDoorOpen","Class":"AdminTools.EventHandlers"},{"Time":0.0074,"Method":"OnPlayerInteractingDoor","Class":"AdminTools.EventHandlers"},{"Time":0.012,"Method":"OnInteractingDoor","Class":"Common_Utilities.EventHandlers.PlayerHandlers"},{"Time":0.0781,"Method":"OnDoorInteract","Class":"RemoteKeycard.EventsHandler"},{"Time":0.0304,"Method":"OnInteractingDoor","Class":"FbiOpenUp.EventHandlers"},{"Time":0.020200000000000003,"Method":"AntiAfkEventHandler","Class":"Common_Utilities.EventHandlers.PlayerHandlers"},{"Time":0.015000000000000001,"Method":"AntiAfkEventHandler","Class":"Common_Utilities.EventHandlers.PlayerHandlers"},{"Time":0.0171,"Method":"AntiAfkEventHandler","Class":"Common_Utilities.EventHandlers.PlayerHandlers"},{"Time":0.015600000000000001,"Method":"AntiAfkEventHandler","Class":"Common_Utilities.EventHandlers.PlayerHandlers"},{"Time":0.015600000000000001,"Method":"AntiAfkEventHandler","Class":"Common_Utilities.EventHandlers.PlayerHandlers"},{"Time":0.020900000000000002,"Method":"AntiAfkEventHandler","Class":"Common_Utilities.EventHandlers.PlayerHandlers"},{"Time":0.0145,"Method":"AntiAfkEventHandler","Class":"Common_Utilities.EventHandlers.PlayerHandlers"},{"Time":0.0158,"Method":"AntiAfkEventHandler","Class":"Common_Utilities.EventHandlers.PlayerHandlers"},{"Time":0.0189,"Method":"AntiAfkEventHandler","Class":"Common_Utilities.EventHandlers.PlayerHandlers"},{"Time":0.021,"Method":"AntiAfkEventHandler","Class":"Common_Utilities.EventHandlers.PlayerHandlers"},{"Time":0.0142,"Method":"AntiAfkEventHandler","Class":"Common_Utilities.EventHandlers.PlayerHandlers"},{"Time":0.042100000000000005,"Method":"OnRoundEnding","Class":"SCPStats.EventHandler"},{"Time":0.0201,"Method":"AntiAfkEventHandler","Class":"Common_Utilities.EventHandlers.PlayerHandlers"},{"Time":0.0152,"Method":"AntiAfkEventHandler","Class":"Common_Utilities.EventHandlers.PlayerHandlers"},{"Time":0.0229,"Method":"OnInteractingDoor","Class":"DiscordIntegration.Events.PlayerHandler"},{"Time":0.0114,"Method":"OnDoorOpen","Class":"AdminTools.EventHandlers"},{"Time":0.0084000000000000012,"Method":"OnPlayerInteractingDoor","Class":"AdminTools.EventHandlers"},{"Time":0.012400000000000001,"Method":"OnInteractingDoor","Class":"Common_Utilities.EventHandlers.PlayerHandlers"},{"Time":0.058100000000000006,"Method":"OnDoorInteract","Class":"RemoteKeycard.EventsHandler"},{"Time":0.029500000000000002,"Method":"OnInteractingDoor","Class":"FbiOpenUp.EventHandlers"},{"Time":0.0216,"Method":"OnInteractingDoor","Class":"DiscordIntegration.Events.PlayerHandler"},{"Time":0.0112,"Method":"OnDoorOpen","Class":"AdminTools.EventHandlers"},{"Time":0.0103,"Method":"OnPlayerInteractingDoor","Class":"AdminTools.EventHandlers"},{"Time":0.014400000000000001,"Method":"OnInteractingDoor","Class":"Common_Utilities.EventHandlers.PlayerHandlers"},{"Time":0.0874,"Method":"OnDoorInteract","Class":"RemoteKeycard.EventsHandler"},{"Time":0.0247,"Method":"OnInteractingDoor","Class":"FbiOpenUp.EventHandlers"},{"Time":0.0252,"Method":"OnInteractingDoor","Class":"DiscordIntegration.Events.PlayerHandler"},{"Time":0.0123,"Method":"OnDoorOpen","Class":"AdminTools.EventHandlers"},{"Time":0.0081,"Method":"OnPlayerInteractingDoor","Class":"AdminTools.EventHandlers"},{"Time":0.0109,"Method":"OnInteractingDoor","Class":"Common_Utilities.EventHandlers.PlayerHandlers"},{"Time":0.0815,"Method":"OnDoorInteract","Class":"RemoteKeycard.EventsHandler"},{"Time":0.033100000000000004,"Method":"OnInteractingDoor","Class":"FbiOpenUp.EventHandlers"},{"Time":0.013600000000000001,"Method":"AntiAfkEventHandler","Class":"Common_Utilities.EventHandlers.PlayerHandlers"},{"Time":0.0172,"Method":"AntiAfkEventHandler","Class":"Common_Utilities.EventHandlers.PlayerHandlers"},{"Time":0.0167,"Method":"AntiAfkEventHandler","Class":"Common_Utilities.EventHandlers.PlayerHandlers"},{"Time":0.022000000000000002,"Method":"AntiAfkEventHandler","Class":"Common_Utilities.EventHandlers.PlayerHandlers"},{"Time":0.015700000000000002,"Method":"AntiAfkEventHandler","Class":"Common_Utilities.EventHandlers.PlayerHandlers"},{"Time":0.024300000000000002,"Method":"OnInteractingDoor","Class":"DiscordIntegration.Events.PlayerHandler"},{"Time":0.0109,"Method":"OnDoorOpen","Class":"AdminTools.EventHandlers"},{"Time":0.0088,"Method":"OnPlayerInteractingDoor","Class":"AdminTools.EventHandlers"},{"Time":0.0115,"Method":"OnInteractingDoor","Class":"Common_Utilities.EventHandlers.PlayerHandlers"},{"Time":0.0323,"Method":"OnDoorInteract","Class":"RemoteKeycard.EventsHandler"},{"Time":0.0273,"Method":"OnInteractingDoor","Class":"FbiOpenUp.EventHandlers"},{"Time":0.019700000000000002,"Method":"AntiAfkEventHandler","Class":"Common_Utilities.EventHandlers.PlayerHandlers"},{"Time":0.019,"Method":"AntiAfkEventHandler","Class":"Common_Utilities.EventHandlers.PlayerHandlers"},{"Time":0.018600000000000002,"Method":"AntiAfkEventHandler","Class":"Common_Utilities.EventHandlers.PlayerHandlers"},{"Time":0.0182,"Method":"AntiAfkEventHandler","Class":"Common_Utilities.EventHandlers.PlayerHandlers"},{"Time":0.0166,"Method":"AntiAfkEventHandler","Class":"Common_Utilities.EventHandlers.PlayerHandlers"},{"Time":0.0154,"Method":"AntiAfkEventHandler","Class":"Common_Utilities.EventHandlers.PlayerHandlers"},{"Time":0.017,"Method":"AntiAfkEventHandler","Class":"Common_Utilities.EventHandlers.PlayerHandlers"},{"Time":0.0143,"Method":"OnRoundEnding","Class":"SCPStats.EventHandler"},{"Time":0.015600000000000001,"Method":"AntiAfkEventHandler","Class":"Common_Utilities.EventHandlers.PlayerHandlers"},{"Time":2.9416,"Method":"OnInteractingElevator","Class":"DiscordIntegration.Events.PlayerHandler"},{"Time":0.623,"Method":"OnInteractingElevator","Class":"Common_Utilities.EventHandlers.PlayerHandlers"},{"Time":0.016300000000000002,"Method":"AntiAfkEventHandler","Class":"Common_Utilities.EventHandlers.PlayerHandlers"},{"Time":0.0171,"Method":"AntiAfkEventHandler","Class":"Common_Utilities.EventHandlers.PlayerHandlers"},{"Time":0.014400000000000001,"Method":"AntiAfkEventHandler","Class":"Common_Utilities.EventHandlers.PlayerHandlers"},{"Time":0.015300000000000001,"Method":"AntiAfkEventHandler","Class":"Common_Utilities.EventHandlers.PlayerHandlers"},{"Time":0.0211,"Method":"AntiAfkEventHandler","Class":"Common_Utilities.EventHandlers.PlayerHandlers"},{"Time":0.0171,"Method":"AntiAfkEventHandler","Class":"Common_Utilities.EventHandlers.PlayerHandlers"},{"Time":0.0189,"Method":"AntiAfkEventHandler","Class":"Common_Utilities.EventHandlers.PlayerHandlers"},{"Time":0.0218,"Method":"AntiAfkEventHandler","Class":"Common_Utilities.EventHandlers.PlayerHandlers"},{"Time":0.0118,"Method":"AntiAfkEventHandler","Class":"Common_Utilities.EventHandlers.PlayerHandlers"},{"Time":0.046700000000000005,"Method":"OnChangingItem","Class":"DiscordIntegration.Events.PlayerHandler"},{"Time":0.028800000000000003,"Method":"OnInteractingDoor","Class":"DiscordIntegration.Events.PlayerHandler"},{"Time":0.014100000000000001,"Method":"OnDoorOpen","Class":"AdminTools.EventHandlers"},{"Time":0.044500000000000005,"Method":"OnPlayerInteractingDoor","Class":"AdminTools.EventHandlers"},{"Time":0.0286,"Method":"OnInteractingDoor","Class":"Common_Utilities.EventHandlers.PlayerHandlers"},{"Time":0.2717,"Method":"OnDoorInteract","Class":"RemoteKeycard.EventsHandler"},{"Time":0.09870000000000001,"Method":"OnInteractingDoor","Class":"FbiOpenUp.EventHandlers"},{"Time":0.0181,"Method":"AntiAfkEventHandler","Class":"Common_Utilities.EventHandlers.PlayerHandlers"},{"Time":0.023,"Method":"OnInteractingDoor","Class":"DiscordIntegration.Events.PlayerHandler"},{"Time":0.013000000000000001,"Method":"OnDoorOpen","Class":"AdminTools.EventHandlers"},{"Time":0.008,"Method":"OnPlayerInteractingDoor","Class":"AdminTools.EventHandlers"},{"Time":0.0115,"Method":"OnInteractingDoor","Class":"Common_Utilities.EventHandlers.PlayerHandlers"},{"Time":0.0322,"Method":"OnDoorInteract","Class":"RemoteKeycard.EventsHandler"},{"Time":0.024800000000000003,"Method":"OnInteractingDoor","Class":"FbiOpenUp.EventHandlers"},{"Time":0.0152,"Method":"AntiAfkEventHandler","Class":"Common_Utilities.EventHandlers.PlayerHandlers"},{"Time":0.0198,"Method":"OnRoundEnding","Class":"SCPStats.EventHandler"},{"Time":2.7902,"Method":"OnTriggeringTesla","Class":"DiscordIntegration.Events.PlayerHandler"},{"Time":0.17830000000000001,"Method":"OnTriggerTesla","Class":"AdminTools.EventHandlers"},{"Time":0.15030000000000002,"Method":"OnTriggeringTesla","Class":"DiscordIntegration.Events.PlayerHandler"},{"Time":0.0135,"Method":"OnTriggerTesla","Class":"AdminTools.EventHandlers"},{"Time":0.1443,"Method":"OnTriggeringTesla","Class":"DiscordIntegration.Events.PlayerHandler"},{"Time":0.013900000000000001,"Method":"OnTriggerTesla","Class":"AdminTools.EventHandlers"},{"Time":0.0173,"Method":"AntiAfkEventHandler","Class":"Common_Utilities.EventHandlers.PlayerHandlers"},{"Time":0.1648,"Method":"OnTriggeringTesla","Class":"DiscordIntegration.Events.PlayerHandler"},{"Time":0.0115,"Method":"OnTriggerTesla","Class":"AdminTools.EventHandlers"},{"Time":0.1575,"Method":"OnTriggeringTesla","Class":"DiscordIntegration.Events.PlayerHandler"},{"Time":0.0098,"Method":"OnTriggerTesla","Class":"AdminTools.EventHandlers"},{"Time":0.1593,"Method":"OnTriggeringTesla","Class":"DiscordIntegration.Events.PlayerHandler"},{"Time":0.0106,"Method":"OnTriggerTesla","Class":"AdminTools.EventHandlers"},{"Time":0.1695,"Method":"OnTriggeringTesla","Class":"DiscordIntegration.Events.PlayerHandler"},{"Time":0.0090000000000000011,"Method":"OnTriggerTesla","Class":"AdminTools.EventHandlers"},{"Time":0.14880000000000002,"Method":"OnTriggeringTesla","Class":"DiscordIntegration.Events.PlayerHandler"},{"Time":0.0099,"Method":"OnTriggerTesla","Class":"AdminTools.EventHandlers"},{"Time":0.1844,"Method":"OnTriggeringTesla","Class":"DiscordIntegration.Events.PlayerHandler"},{"Time":0.011600000000000001,"Method":"OnTriggerTesla","Class":"AdminTools.EventHandlers"},{"Time":0.18560000000000001,"Method":"OnTriggeringTesla","Class":"DiscordIntegration.Events.PlayerHandler"},{"Time":0.0099,"Method":"OnTriggerTesla","Class":"AdminTools.EventHandlers"},{"Time":0.19460000000000002,"Method":"OnTriggeringTesla","Class":"DiscordIntegration.Events.PlayerHandler"},{"Time":0.0731,"Method":"OnTriggerTesla","Class":"AdminTools.EventHandlers"},{"Time":0.269,"Method":"OnTriggeringTesla","Class":"DiscordIntegration.Events.PlayerHandler"},{"Time":0.0112,"Method":"OnTriggerTesla","Class":"AdminTools.EventHandlers"},{"Time":0.663,"Method":"OnTriggeringTesla","Class":"DiscordIntegration.Events.PlayerHandler"},{"Time":0.0634,"Method":"OnTriggerTesla","Class":"AdminTools.EventHandlers"},{"Time":0.2137,"Method":"OnTriggeringTesla","Class":"DiscordIntegration.Events.PlayerHandler"},{"Time":0.0158,"Method":"OnTriggerTesla","Class":"AdminTools.EventHandlers"},{"Time":0.499,"Method":"OnTriggeringTesla","Class":"DiscordIntegration.Events.PlayerHandler"},{"Time":0.0128,"Method":"OnTriggerTesla","Class":"AdminTools.EventHandlers"},{"Time":0.27290000000000003,"Method":"OnTriggeringTesla","Class":"DiscordIntegration.Events.PlayerHandler"},{"Time":0.013300000000000001,"Method":"OnTriggerTesla","Class":"AdminTools.EventHandlers"},{"Time":0.2054,"Method":"OnTriggeringTesla","Class":"DiscordIntegration.Events.PlayerHandler"},{"Time":0.0112,"Method":"OnTriggerTesla","Class":"AdminTools.EventHandlers"},{"Time":0.1857,"Method":"OnTriggeringTesla","Class":"DiscordIntegration.Events.PlayerHandler"},{"Time":0.0105,"Method":"OnTriggerTesla","Class":"AdminTools.EventHandlers"},{"Time":0.0167,"Method":"AntiAfkEventHandler","Class":"Common_Utilities.EventHandlers.PlayerHandlers"},{"Time":0.019,"Method":"AntiAfkEventHandler","Class":"Common_Utilities.EventHandlers.PlayerHandlers"},{"Time":0.2426,"Method":"OnTriggeringTesla","Class":"DiscordIntegration.Events.PlayerHandler"},{"Time":0.0164,"Method":"OnTriggerTesla","Class":"AdminTools.EventHandlers"},{"Time":0.0291,"Method":"OnRoundEnding","Class":"SCPStats.EventHandler"},{"Time":0.0262,"Method":"AntiAfkEventHandler","Class":"Common_Utilities.EventHandlers.PlayerHandlers"},{"Time":0.026000000000000002,"Method":"AntiAfkEventHandler","Class":"Common_Utilities.EventHandlers.PlayerHandlers"},{"Time":0.0371,"Method":"OnInteractingDoor","Class":"DiscordIntegration.Events.PlayerHandler"},{"Time":0.0543,"Method":"OnDoorOpen","Class":"AdminTools.EventHandlers"},{"Time":0.028800000000000003,"Method":"OnPlayerInteractingDoor","Class":"AdminTools.EventHandlers"},{"Time":0.024800000000000003,"Method":"OnInteractingDoor","Class":"Common_Utilities.EventHandlers.PlayerHandlers"},{"Time":0.0637,"Method":"OnDoorInteract","Class":"RemoteKeycard.EventsHandler"},{"Time":0.048100000000000004,"Method":"OnInteractingDoor","Class":"FbiOpenUp.EventHandlers"},{"Time":0.020300000000000002,"Method":"AntiAfkEventHandler","Class":"Common_Utilities.EventHandlers.PlayerHandlers"},{"Time":0.0335,"Method":"OnInteractingDoor","Class":"DiscordIntegration.Events.PlayerHandler"},{"Time":0.013900000000000001,"Method":"OnDoorOpen","Class":"AdminTools.EventHandlers"},{"Time":0.0083,"Method":"OnPlayerInteractingDoor","Class":"AdminTools.EventHandlers"},{"Time":0.0161,"Method":"OnInteractingDoor","Class":"Common_Utilities.EventHandlers.PlayerHandlers"},{"Time":0.0465,"Method":"OnDoorInteract","Class":"RemoteKeycard.EventsHandler"},{"Time":0.034300000000000004,"Method":"OnInteractingDoor","Class":"FbiOpenUp.EventHandlers"},{"Time":0.019200000000000002,"Method":"AntiAfkEventHandler","Class":"Common_Utilities.EventHandlers.PlayerHandlers"},{"Time":0.0179,"Method":"AntiAfkEventHandler","Class":"Common_Utilities.EventHandlers.PlayerHandlers"},{"Time":0.042100000000000005,"Method":"OnRoundEnding","Class":"SCPStats.EventHandler"},{"Time":0.0155,"Method":"AntiAfkEventHandler","Class":"Common_Utilities.EventHandlers.PlayerHandlers"},{"Time":0.015300000000000001,"Method":"AntiAfkEventHandler","Class":"Common_Utilities.EventHandlers.PlayerHandlers"},{"Time":0.0158,"Method":"AntiAfkEventHandler","Class":"Common_Utilities.EventHandlers.PlayerHandlers"},{"Time":0.027200000000000002,"Method":"OnInteractingDoor","Class":"DiscordIntegration.Events.PlayerHandler"},{"Time":0.0335,"Method":"OnDoorOpen","Class":"AdminTools.EventHandlers"},{"Time":0.0118,"Method":"OnPlayerInteractingDoor","Class":"AdminTools.EventHandlers"},{"Time":0.0114,"Method":"OnInteractingDoor","Class":"Common_Utilities.EventHandlers.PlayerHandlers"},{"Time":0.054900000000000004,"Method":"OnDoorInteract","Class":"RemoteKeycard.EventsHandler"},{"Time":0.0385,"Method":"OnInteractingDoor","Class":"FbiOpenUp.EventHandlers"},{"Time":0.017,"Method":"AntiAfkEventHandler","Class":"Common_Utilities.EventHandlers.PlayerHandlers"},{"Time":0.0332,"Method":"OnInteractingDoor","Class":"DiscordIntegration.Events.PlayerHandler"},{"Time":0.0166,"Method":"OnDoorOpen","Class":"AdminTools.EventHandlers"},{"Time":0.0112,"Method":"OnPlayerInteractingDoor","Class":"AdminTools.EventHandlers"},{"Time":0.0125,"Method":"OnInteractingDoor","Class":"Common_Utilities.EventHandlers.PlayerHandlers"},{"Time":0.0318,"Method":"OnDoorInteract","Class":"RemoteKeycard.EventsHandler"},{"Time":0.0269,"Method":"OnInteractingDoor","Class":"FbiOpenUp.EventHandlers"},{"Time":0.0072000000000000007,"Method":"AntiAfkEventHandler","Class":"Common_Utilities.EventHandlers.PlayerHandlers"},{"Time":0.0151,"Method":"AntiAfkEventHandler","Class":"Common_Utilities.EventHandlers.PlayerHandlers"},{"Time":0.016,"Method":"OnRoundEnding","Class":"SCPStats.EventHandler"},{"Time":0.0176,"Method":"AntiAfkEventHandler","Class":"Common_Utilities.EventHandlers.PlayerHandlers"},{"Time":0.015300000000000001,"Method":"AntiAfkEventHandler","Class":"Common_Utilities.EventHandlers.PlayerHandlers"},{"Time":0.0181,"Method":"AntiAfkEventHandler","Class":"Common_Utilities.EventHandlers.PlayerHandlers"},{"Time":0.0235,"Method":"OnRoundEnding","Class":"SCPStats.EventHandler"},{"Time":0.0206,"Method":"AntiAfkEventHandler","Class":"Common_Utilities.EventHandlers.PlayerHandlers"},{"Time":0.014,"Method":"AntiAfkEventHandler","Class":"Common_Utilities.EventHandlers.PlayerHandlers"},{"Time":0.018000000000000002,"Method":"AntiAfkEventHandler","Class":"Common_Utilities.EventHandlers.PlayerHandlers"},{"Time":0.023200000000000002,"Method":"AntiAfkEventHandler","Class":"Common_Utilities.EventHandlers.PlayerHandlers"},{"Time":0.0194,"Method":"AntiAfkEventHandler","Class":"Common_Utilities.EventHandlers.PlayerHandlers"},{"Time":0.0171,"Method":"OnRoundEnding","Class":"SCPStats.EventHandler"},{"Time":0.0339,"Method":"AntiAfkEventHandler","Class":"Common_Utilities.EventHandlers.PlayerHandlers"},{"Time":0.0117,"Method":"AntiAfkEventHandler","Class":"Common_Utilities.EventHandlers.PlayerHandlers"},{"Time":0.0502,"Method":"OnInteractingDoor","Class":"DiscordIntegration.Events.PlayerHandler"},{"Time":0.032600000000000004,"Method":"OnDoorOpen","Class":"AdminTools.EventHandlers"},{"Time":0.0183,"Method":"OnPlayerInteractingDoor","Class":"AdminTools.EventHandlers"},{"Time":0.021400000000000002,"Method":"OnInteractingDoor","Class":"Common_Utilities.EventHandlers.PlayerHandlers"},{"Time":0.0524,"Method":"OnDoorInteract","Class":"RemoteKeycard.EventsHandler"},{"Time":0.0529,"Method":"OnInteractingDoor","Class":"FbiOpenUp.EventHandlers"},{"Time":0.0279,"Method":"OnInteractingDoor","Class":"DiscordIntegration.Events.PlayerHandler"},{"Time":0.014400000000000001,"Method":"OnDoorOpen","Class":"AdminTools.EventHandlers"},{"Time":0.0096000000000000009,"Method":"OnPlayerInteractingDoor","Class":"AdminTools.EventHandlers"},{"Time":0.013900000000000001,"Method":"OnInteractingDoor","Class":"Common_Utilities.EventHandlers.PlayerHandlers"},{"Time":0.0386,"Method":"OnDoorInteract","Class":"RemoteKeycard.EventsHandler"},{"Time":0.0313,"Method":"OnInteractingDoor","Class":"FbiOpenUp.EventHandlers"},{"Time":0.0161,"Method":"AntiAfkEventHandler","Class":"Common_Utilities.EventHandlers.PlayerHandlers"},{"Time":0.019700000000000002,"Method":"AntiAfkEventHandler","Class":"Common_Utilities.EventHandlers.PlayerHandlers"},{"Time":0.0056,"Method":"AntiAfkEventHandler","Class":"Common_Utilities.EventHandlers.PlayerHandlers"},{"Time":0.0176,"Method":"AntiAfkEventHandler","Class":"Common_Utilities.EventHandlers.PlayerHandlers"},{"Time":0.016800000000000002,"Method":"AntiAfkEventHandler","Class":"Common_Utilities.EventHandlers.PlayerHandlers"},{"Time":0.024800000000000003,"Method":"OnRoundEnding","Class":"SCPStats.EventHandler"},{"Time":0.0177,"Method":"AntiAfkEventHandler","Class":"Common_Utilities.EventHandlers.PlayerHandlers"},{"Time":0.0179,"Method":"AntiAfkEventHandler","Class":"Common_Utilities.EventHandlers.PlayerHandlers"},{"Time":0.021,"Method":"AntiAfkEventHandler","Class":"Common_Utilities.EventHandlers.PlayerHandlers"},{"Time":0.0218,"Method":"AntiAfkEventHandler","Class":"Common_Utilities.EventHandlers.PlayerHandlers"},{"Time":0.017,"Method":"AntiAfkEventHandler","Class":"Common_Utilities.EventHandlers.PlayerHandlers"},{"Time":0.0159,"Method":"AntiAfkEventHandler","Class":"Common_Utilities.EventHandlers.PlayerHandlers"},{"Time":0.013900000000000001,"Method":"AntiAfkEventHandler","Class":"Common_Utilities.EventHandlers.PlayerHandlers"},{"Time":0.014400000000000001,"Method":"AntiAfkEventHandler","Class":"Common_Utilities.EventHandlers.PlayerHandlers"},{"Time":0.0142,"Method":"AntiAfkEventHandler","Class":"Common_Utilities.EventHandlers.PlayerHandlers"},{"Time":0.0155,"Method":"AntiAfkEventHandler","Class":"Common_Utilities.EventHandlers.PlayerHandlers"},{"Time":0.015700000000000002,"Method":"OnRoundEnding","Class":"SCPStats.EventHandler"},{"Time":0.0158,"Method":"AntiAfkEventHandler","Class":"Common_Utilities.EventHandlers.PlayerHandlers"},{"Time":0.0236,"Method":"AntiAfkEventHandler","Class":"Common_Utilities.EventHandlers.PlayerHandlers"},{"Time":0.0363,"Method":"AntiAfkEventHandler","Class":"Common_Utilities.EventHandlers.PlayerHandlers"},{"Time":0.0155,"Method":"AntiAfkEventHandler","Class":"Common_Utilities.EventHandlers.PlayerHandlers"},{"Time":0.0184,"Method":"AntiAfkEventHandler","Class":"Common_Utilities.EventHandlers.PlayerHandlers"}]